streamlit_gps_location/__init__.py
streamlit_gps_location/example.py
streamlit_gps_location/frontend/build/asset-manifest.json
streamlit_gps_location/frontend/build/bootstrap.min.css
streamlit_gps_location/frontend/build/index.html
streamlit_gps_location/frontend/build/static/css/main.65529acf.css
streamlit_gps_location/frontend/build/static/css/main.65529acf.css.map
streamlit_gps_location/frontend/build/static/css/main.72768c64.css
streamlit_gps_location/frontend/build/static/css/main.72768c64.css.map
streamlit_gps_location/frontend/build/static/css/main.8cc6da8e.css
streamlit_gps_location/frontend/build/static/css/main.8cc6da8e.css.map
streamlit_gps_location/frontend/build/static/css/main.f3700595.css
streamlit_gps_location/frontend/build/static/css/main.f3700595.css.map
streamlit_gps_location/frontend/build/static/js/main.1d03ca9c.js
streamlit_gps_location/frontend/build/static/js/main.1d03ca9c.js.LICENSE.txt
streamlit_gps_location/frontend/build/static/js/main.1d03ca9c.js.map
streamlit_gps_location/frontend/build/static/js/main.55219985.js
streamlit_gps_location/frontend/build/static/js/main.55219985.js.LICENSE.txt
streamlit_gps_location/frontend/build/static/js/main.55219985.js.map
streamlit_gps_location/frontend/build/static/js/main.5bd1bd22.js
streamlit_gps_location/frontend/build/static/js/main.5bd1bd22.js.LICENSE.txt
streamlit_gps_location/frontend/build/static/js/main.5bd1bd22.js.map
streamlit_gps_location/frontend/build/static/js/main.5d3feb5a.js
streamlit_gps_location/frontend/build/static/js/main.5d3feb5a.js.LICENSE.txt
streamlit_gps_location/frontend/build/static/js/main.5d3feb5a.js.map
streamlit_gps_location/frontend/build/static/js/main.739bbd97.js
streamlit_gps_location/frontend/build/static/js/main.739bbd97.js.LICENSE.txt
streamlit_gps_location/frontend/build/static/js/main.739bbd97.js.map
streamlit_gps_location/frontend/build/static/js/main.80719449.js
streamlit_gps_location/frontend/build/static/js/main.80719449.js.LICENSE.txt
streamlit_gps_location-1.2.2.dist-info/LICENSE
streamlit_gps_location-1.2.2.dist-info/METADATA
streamlit_gps_location-1.2.2.dist-info/WHEEL
streamlit_gps_location-1.2.2.dist-info/top_level.txt
streamlit_gps_location-1.2.2.dist-info/RECORD
